{
    "Flusight-baseline": {
        "target_end_date": [
            "2022-10-22",
            "2022-10-29",
            "2022-11-05",
            "2022-11-12"
        ],
        "q0.025": [
            62.0,
            39.0,
            38.0,
            27.0
        ],
        "q0.25": [
            86.0,
            64.0,
            74.0,
            66.0
        ],
        "q0.5": [
            96.0,
            76.0,
            93.0,
            87.0
        ],
        "q0.75": [
            106.0,
            89.0,
            111.0,
            107.0
        ],
        "q0.975": [
            130.0,
            113.0,
            148.0,
            147.0
        ]
    },
    "MOBS-GLEAM_FLUH": {
        "target_end_date": [
            "2022-10-22",
            "2022-10-29",
            "2022-11-05",
            "2022-11-12"
        ],
        "q0.025": [
            76.0,
            118.0,
            137.0,
            199.0
        ],
        "q0.25": [
            98.0,
            173.0,
            229.0,
            361.0
        ],
        "q0.5": [
            114.0,
            222.0,
            320.0,
            522.0
        ],
        "q0.75": [
            135.0,
            297.0,
            470.0,
            789.0
        ],
        "q0.975": [
            190.0,
            535.0,
            987.0,
            1698.0
        ]
    },
    "PSI-DICE": {
        "target_end_date": [
            "2022-10-22",
            "2022-10-29",
            "2022-11-05",
            "2022-11-12"
        ],
        "q0.025": [
            60.0,
            88.0,
            106.0,
            167.0
        ],
        "q0.25": [
            78.0,
            114.0,
            133.0,
            208.0
        ],
        "q0.5": [
            89.0,
            130.0,
            153.0,
            238.0
        ],
        "q0.75": [
            101.0,
            149.0,
            177.0,
            277.0
        ],
        "q0.975": [
            124.0,
            182.0,
            214.0,
            332.0
        ]
    }
}